bins/analyze.py
bins/measure.py
src/analysis_modules/draw_ecdf.py
src/db_crud/__init__.py
src/db_crud/read.py
modular_time_fuzzer_GOGO-0.0.1.dist-info/METADATA
modular_time_fuzzer_GOGO-0.0.1.dist-info/WHEEL
modular_time_fuzzer_GOGO-0.0.1.dist-info/entry_points.txt
modular_time_fuzzer_GOGO-0.0.1.dist-info/top_level.txt
modular_time_fuzzer_GOGO-0.0.1.dist-info/RECORD
