Metadata-Version: 2.1
Name: modular_time_fuzzer_GOGO
Version: 0.0.1
Summary: modular time fuzzer
Author-email: gogo246475 <gogo246475@gmail.com>
Project-URL: Homepage, https://github.com/pypa/sampleproject
Project-URL: Issues, https://github.com/pypa/sampleproject/issues
Classifier: Programming Language :: Python :: 3
Classifier: Operating System :: OS Independent
Requires-Python: >=3.8
Requires-Dist: requests
Requires-Dist: argparse
